[
  {
    "Id": 1,
    "Type": 2,
    "backgroundName": "Школа",
    "nextEventId": 2
  },
  {
    "text": "Привет. Ты загрузил вторую часть сценария.",
    "speakerName": "Алиса",
    "nextEventId": 3,
    "Id": 2,
    "Type": 0
  },
  {
    "text": "В этой части есть несколько концовок.",
    "speakerName": "Алиса",
    "nextEventId": 4,
    "Id": 3,
    "Type": 0
  },
  {
    "text": "Только ты можешь повлиять на то, чем она закончится.",
    "speakerName": "Алиса",
    "nextEventId": 5,
    "Id": 4,
    "Type": 0
  },
  
  
  {
    "header": "Так что же ты выберешь?",
    "canUseDefender": true,
    "defenderCost": 20,
    "choices": [
      {
        "choiceText": "Что за части? Что за концовки?",
        "defenderText": "Я хочу повторить эту часть",
        "resultId": 6
      },
      {
        "choiceText": "Хорошо, я понял. Я не ошибусь!",
        "defenderText": "Я хочу пройти эту часть",
        "resultId": 7
      },
      {
        "choiceText": "Подожди, можно помедленнее?",
        "defenderText": "Я хочу получить инструкцию",
        "resultId": 8
      }
    ],
    "Id": 5,
    "Type": 1
  },
  {
    "Id": 6,
    "nextEventId": 20,
    "text": "Похоже, тебе ещё многому надо учиться.",
    "speakerName": "Максим",
    "Type": 0
  },
  {
    "Id": 20,
    "text": "Иногда даже невинный вопрос может всё испортить.",
    "Type": 999,
    "isChapterCompleted": false
  },
  {
    "Id": 7,
    "nextEventId": 30,
    "text": "Смотри, не подведи нас. Мы надеемся на тебя.",
    "speakerName": "Максим",
    "Type": 0
  },
  {
    "Id": 30,
    "text": "Полный уверенности в своей правоте, ты шагаешь вперёд.",
    "Type": 999,
    "isChapterCompleted": true
  },
  {
    "Id": 8,
    "text": "Теперь в json-файлах ты можешь указывать, завершена ли часть.",
    "speakerName": "Марина",
    "nextEventId": 9,
    "Type": 0
  },
  {
    "Id": 9,
    "text": "В элементах с полем Type, в котором записано 999, появилось ещё одно поле.",
    "speakerName": "Марина",
    "nextEventId": 10,
    "Type": 0
  },
  {
    "Id": 10,
    "text": "Это поле называется isChapterCompleted.",
    "speakerName": "Марина",
    "nextEventId": 11,
    "Type": 0
  },
  {
    "Id": 11,
    "text": "Если в нём записано true, то в конце сценария тебе откроется следующий.",
    "speakerName": "Марина",
    "nextEventId": 12,
    "Type": 0
  },
  {
    "Id": 12,
    "text": "В противном случае ты должен будешь переиграть сценарий заново",
    "speakerName": "Марина",
    "nextEventId": 13,
    "Type": 0
  },
  {
    "Id": 13,
    "text": "Будь осторожен! По умолчанию там записано false!",
    "speakerName": "Марина",
    "nextEventId": 5,
    "Type": 0
  }
]
